complex_text_tools/__init__.py
complex_text_tools/text_processor.py
complex_text_tools-0.2.4.dist-info/LICENSE
complex_text_tools-0.2.4.dist-info/METADATA
complex_text_tools-0.2.4.dist-info/WHEEL
complex_text_tools-0.2.4.dist-info/top_level.txt
complex_text_tools-0.2.4.dist-info/RECORD
