Metadata-Version: 2.1
Name: complex-text-tools
Version: 0.2.4
Summary: A package for processing complex text with mixed Chinese and English characters
Home-page: https://github.com/mooremok/complex-text-tools
Author: mooremok
Author-email: mooremok <mooremok@163.com>
License: MIT
Project-URL: Homepage, https://github.com/mooremok/complex-text-tools
Classifier: Development Status :: 3 - Alpha
Classifier: Intended Audience :: Developers
Classifier: License :: OSI Approved :: MIT License
Classifier: Operating System :: OS Independent
Classifier: Programming Language :: Python :: 3
Classifier: Programming Language :: Python :: 3.6
Classifier: Programming Language :: Python :: 3.7
Classifier: Programming Language :: Python :: 3.8
Classifier: Programming Language :: Python :: 3.9
Classifier: Programming Language :: Python :: 3.10
Classifier: Topic :: Text Processing :: Linguistic
Requires-Python: >=3.6
License-File: LICENSE
Provides-Extra: dev
Requires-Dist: pytest>=6.0; extra == "dev"
